mesh_rpc/__init__.py
mesh_rpc/_chain.pravah.io.crt
mesh_rpc/auth_gateway.py
mesh_rpc/ca.rpc.pravah.io.crt
mesh_rpc/chain.pravah.io.crt
mesh_rpc/crypto.py
mesh_rpc/exp.py
mesh_rpc/mesh.py
mesh_rpc/util.py
mesh_rpc/lib/__init__.py
mesh_rpc/lib/rpc_pb2.py
mesh_rpc/lib/rpc_pb2_grpc.py
mesh_rpc-0.1.6.dist-info/LICENSE
mesh_rpc-0.1.6.dist-info/METADATA
mesh_rpc-0.1.6.dist-info/WHEEL
mesh_rpc-0.1.6.dist-info/top_level.txt
mesh_rpc-0.1.6.dist-info/RECORD
