Metadata-Version: 2.1
Name: mesh-rpc
Version: 0.1.6
Summary: RPC library for mesh-pravah
Home-page: https://github.com/pravahio
Author: Abhishek Upperwal
Author-email: mesh@soket.in
License: UNKNOWN
Platform: UNKNOWN
Classifier: Programming Language :: Python :: 3
Classifier: License :: OSI Approved :: MIT License
Classifier: Operating System :: OS Independent
Requires-Dist: grpcio
